tawkto/__init__.py
tawkto/apps.py
tawkto/templates/tawkto/templatetags/tawkto_script.html
django_tawkto-0.4.dist-info/LICENSE
django_tawkto-0.4.dist-info/METADATA
django_tawkto-0.4.dist-info/WHEEL
django_tawkto-0.4.dist-info/top_level.txt
django_tawkto-0.4.dist-info/RECORD
